{
  "openapi": "3.0.0",
  "info": {
    "title": "media-service API",
    "version": "1.0.0",
    "description": "Auto-generated API spec for media-service. Generated by Milonexa AI Admin Agent v2.2.",
    "x-generated-at": "2026-03-11T17:45:04.690Z"
  },
  "servers": [
    {
      "url": "http://localhost:8000",
      "description": "API Gateway"
    }
  ],
  "paths": {
    "/health": {
      "get": {
        "summary": "GET /health",
        "description": "Auto-extracted from media-service/server.js",
        "operationId": "get_health",
        "responses": {
          "200": {
            "description": "Success"
          },
          "400": {
            "description": "Bad request"
          },
          "401": {
            "description": "Unauthorized"
          },
          "500": {
            "description": "Internal server error"
          }
        },
        "tags": [
          "media-service"
        ]
      }
    },
    "/health/ready": {
      "get": {
        "summary": "GET /health/ready",
        "description": "Auto-extracted from media-service/server.js",
        "operationId": "get_health_ready",
        "responses": {
          "200": {
            "description": "Success"
          },
          "400": {
            "description": "Bad request"
          },
          "401": {
            "description": "Unauthorized"
          },
          "500": {
            "description": "Internal server error"
          }
        },
        "tags": [
          "media-service"
        ]
      }
    },
    "/metrics": {
      "get": {
        "summary": "GET /metrics",
        "description": "Auto-extracted from media-service/server.js",
        "operationId": "get_metrics",
        "responses": {
          "200": {
            "description": "Success"
          },
          "400": {
            "description": "Bad request"
          },
          "401": {
            "description": "Unauthorized"
          },
          "500": {
            "description": "Internal server error"
          }
        },
        "tags": [
          "media-service"
        ]
      }
    },
    "/debug/query-stats": {
      "get": {
        "summary": "GET /debug/query-stats",
        "description": "Auto-extracted from media-service/server.js",
        "operationId": "get_debug_query_stats",
        "responses": {
          "200": {
            "description": "Success"
          },
          "400": {
            "description": "Bad request"
          },
          "401": {
            "description": "Unauthorized"
          },
          "500": {
            "description": "Internal server error"
          }
        },
        "tags": [
          "media-service"
        ]
      }
    },
    "/url/:fileId": {
      "get": {
        "summary": "GET /url/:fileId",
        "description": "Auto-extracted from media-service/server.js",
        "operationId": "get_url_fileId",
        "responses": {
          "200": {
            "description": "Success"
          },
          "400": {
            "description": "Bad request"
          },
          "401": {
            "description": "Unauthorized"
          },
          "500": {
            "description": "Internal server error"
          }
        },
        "tags": [
          "media-service"
        ]
      }
    },
    "/upload": {
      "post": {
        "summary": "POST /upload",
        "description": "Auto-extracted from media-service/server.js",
        "operationId": "post_upload",
        "responses": {
          "200": {
            "description": "Success"
          },
          "400": {
            "description": "Bad request"
          },
          "401": {
            "description": "Unauthorized"
          },
          "500": {
            "description": "Internal server error"
          }
        },
        "tags": [
          "media-service"
        ]
      }
    },
    "/": {
      "get": {
        "summary": "GET /",
        "description": "Auto-extracted from media-service/server.js",
        "operationId": "get_",
        "responses": {
          "200": {
            "description": "Success"
          },
          "400": {
            "description": "Bad request"
          },
          "401": {
            "description": "Unauthorized"
          },
          "500": {
            "description": "Internal server error"
          }
        },
        "tags": [
          "media-service"
        ]
      }
    }
  }
}